odoo/addons/edi_exchange_template_oca/README.rst
odoo/addons/edi_exchange_template_oca/__init__.py
odoo/addons/edi_exchange_template_oca/__manifest__.py
odoo/addons/edi_exchange_template_oca/utils.py
odoo/addons/edi_exchange_template_oca/components/__init__.py
odoo/addons/edi_exchange_template_oca/components/common.py
odoo/addons/edi_exchange_template_oca/components/output_mixin.py
odoo/addons/edi_exchange_template_oca/i18n/edi_exchange_template.pot
odoo/addons/edi_exchange_template_oca/i18n/edi_exchange_template_oca.pot
odoo/addons/edi_exchange_template_oca/i18n/es.po
odoo/addons/edi_exchange_template_oca/models/__init__.py
odoo/addons/edi_exchange_template_oca/models/edi_backend.py
odoo/addons/edi_exchange_template_oca/models/edi_exchange_template_mixin.py
odoo/addons/edi_exchange_template_oca/models/edi_exchange_template_output.py
odoo/addons/edi_exchange_template_oca/readme/CONTRIBUTORS.rst
odoo/addons/edi_exchange_template_oca/readme/DESCRIPTION.rst
odoo/addons/edi_exchange_template_oca/security/ir_model_access.xml
odoo/addons/edi_exchange_template_oca/static/description/icon.png
odoo/addons/edi_exchange_template_oca/static/description/index.html
odoo/addons/edi_exchange_template_oca/tests/__init__.py
odoo/addons/edi_exchange_template_oca/tests/test_edi_backend_output.py
odoo/addons/edi_exchange_template_oca/tests/test_nswrapper.py
odoo/addons/edi_exchange_template_oca/views/edi_exchange_template_output_views.xml
odoo14_addon_edi_exchange_template_oca-14.0.1.5.2.dist-info/METADATA
odoo14_addon_edi_exchange_template_oca-14.0.1.5.2.dist-info/WHEEL
odoo14_addon_edi_exchange_template_oca-14.0.1.5.2.dist-info/top_level.txt
odoo14_addon_edi_exchange_template_oca-14.0.1.5.2.dist-info/RECORD
